pazel/__init__.py
pazel/app.py
pazel/bazel_rules.py
pazel/generate_rule.py
pazel/helpers.py
pazel/import_inference_rules.py
pazel/output_build.py
pazel/parse_build.py
pazel/parse_imports.py
pazel/pazel_extensions.py
pazel/tests/__init__.py
pazel/tests/test_bazel_rules.py
pazel/tests/test_generate_rule.py
pazel/tests/test_helpers.py
pazel/tests/test_parse_imports.py
pazel/tests/test_pazel_extensions.py
pazel-0.1.0.dist-info/LICENSE
pazel-0.1.0.dist-info/METADATA
pazel-0.1.0.dist-info/WHEEL
pazel-0.1.0.dist-info/entry_points.txt
pazel-0.1.0.dist-info/top_level.txt
pazel-0.1.0.dist-info/RECORD
