Metadata-Version: 2.1
Name: pazel
Version: 0.1.0
Summary: Generate Bazel BUILD files for a Python project.
Home-page: https://github.com/tuomasr/pazel
Author: Tuomas Rintamaki
License: UNKNOWN
Keywords: automation
Platform: UNKNOWN
Classifier: Topic :: Software Development :: Build Tools
Classifier: License :: OSI Approved :: MIT License
Classifier: Operating System :: OS Independent
